mebo/__init__.py
mebo/exceptions.py
mebo/mebo.py
mebo/stream/__init__.py
mebo/stream/auth.py
mebo/stream/decode.py
mebo/stream/rtp.py
mebo/stream/rtsp.py
mebo/stream/sdp.py
mebo/stream/session.py
mebo-0.1.0.dev4.dist-info/DESCRIPTION.rst
mebo-0.1.0.dev4.dist-info/METADATA
mebo-0.1.0.dev4.dist-info/RECORD
mebo-0.1.0.dev4.dist-info/WHEEL
mebo-0.1.0.dev4.dist-info/metadata.json
mebo-0.1.0.dev4.dist-info/top_level.txt
