Metadata-Version: 2.0
Name: mebo
Version: 0.1.0.dev4
Summary: Simple python interface to control the mebo toy robot
Home-page: https://github.com/crlane/python-mebo
Author: Cameron Lane
Author-email: crlane@adamanteus.com
License: MIT
Platform: UNKNOWN
Classifier: Development Status :: 3 - Alpha
Classifier: Intended Audience :: Education
Classifier: Topic :: Scientific/Engineering :: Human Machine Interfaces
Classifier: License :: OSI Approved :: MIT License
Classifier: Programming Language :: Python :: 3
Classifier: Programming Language :: Python :: 3.6
Requires-Dist: requests
Provides-Extra: development
Requires-Dist: ipdb; extra == 'development'
Requires-Dist: ipython; extra == 'development'
Provides-Extra: testing
Requires-Dist: coverage; extra == 'testing'
Requires-Dist: pytest; extra == 'testing'
Requires-Dist: pytest-cov; extra == 'testing'
Requires-Dist: python-coveralls; extra == 'testing'
